CHANGES.txt
LICENSE.txt
MANIFEST.in
README.rst
setup.py
docs/images/Logo_blue_transparent_64.png
docs/images/read_img_austria.png
docs/images/read_ts_austria.png
poets/__init__.py
poets/poet.py
poets.egg-info/PKG-INFO
poets.egg-info/SOURCES.txt
poets.egg-info/dependency_links.txt
poets.egg-info/requires.txt
poets.egg-info/top_level.txt
poets/grid/__init__.py
poets/grid/grids.py
poets/image/__init__.py
poets/image/geotiff.py
poets/image/imagefile.py
poets/image/netcdf.py
poets/image/resampling.py
poets/io/__init__.py
poets/io/download.py
poets/io/source_base.py
poets/shape/__init__.py
poets/shape/shapes.py
poets/shape/ancillary/world_country_admin_boundary_shapefile_with_fips_codes.README
poets/shape/ancillary/world_country_admin_boundary_shapefile_with_fips_codes.dbf
poets/shape/ancillary/world_country_admin_boundary_shapefile_with_fips_codes.shp
poets/shape/ancillary/world_country_admin_boundary_shapefile_with_fips_codes.shx
poets/timedate/__init__.py
poets/timedate/dateindex.py
poets/timedate/dekad.py
poets/web/__init__.py
poets/web/app.py
poets/web/overlays.py
poets/web/static/favicon.ico
poets/web/static/poets_logo_white_32.png
poets/web/static/js/dygraph-combined.js
poets/web/static/js/poets.js
poets/web/static/ol2.13.1/OpenLayers.js
poets/web/static/ol2.13.1/OpenLayers.light.js
poets/web/static/ol2.13.1/OpenLayers.mobile.js
poets/web/static/ol2.13.1/authors.txt
poets/web/static/ol2.13.1/license.txt
poets/web/static/ol2.13.1/readme.md
poets/web/static/ol2.13.1/img/blank.gif
poets/web/static/ol2.13.1/img/cloud-popup-relative.png
poets/web/static/ol2.13.1/img/drag-rectangle-off.png
poets/web/static/ol2.13.1/img/drag-rectangle-on.png
poets/web/static/ol2.13.1/img/east-mini.png
poets/web/static/ol2.13.1/img/layer-switcher-maximize.png
poets/web/static/ol2.13.1/img/layer-switcher-minimize.png
poets/web/static/ol2.13.1/img/marker-blue.png
poets/web/static/ol2.13.1/img/marker-gold.png
poets/web/static/ol2.13.1/img/marker-green.png
poets/web/static/ol2.13.1/img/marker.png
poets/web/static/ol2.13.1/img/measuring-stick-off.png
poets/web/static/ol2.13.1/img/measuring-stick-on.png
