Metadata-Version: 1.0
Name: poets
Version: 0.3.0
Summary: python Open Earth Observation Tools
Home-page: http://rs.geo.tuwien.ac.at/poets
Author: poets Team
Author-email: Thomas.Mistelbauer@geo.tuwien.ac.at
License: LICENSE.txt
Platform: UNKNOWN
